maths_ops/__init__.py
maths_ops-0.0.1.dist-info/LICENSE.txt
maths_ops-0.0.1.dist-info/METADATA
maths_ops-0.0.1.dist-info/WHEEL
maths_ops-0.0.1.dist-info/top_level.txt
maths_ops-0.0.1.dist-info/RECORD
