Metadata-Version: 2.1
Name: maths-ops
Version: 0.0.1
Summary: This python module contains total of 10  functions for doing basic mathematical operations
Home-page: https://github.com/sachiniitdelhi2021/First-published-python-module-
Author: Sachin Dangi
Author-email: sachiniit36@gmail.com
License: UNKNOWN
Keywords: maths,maths_ops,maths_operations
Platform: UNKNOWN
Classifier: Programming Language :: Python :: 3
Classifier: License :: OSI Approved :: MIT License
Classifier: Operating System :: OS Independent
Requires-Python: >=3.6
License-File: LICENSE.txt
